streamdeck_ui/__init__.py
streamdeck_ui/api.py
streamdeck_ui/button.ui
streamdeck_ui/cli/__init__.py
streamdeck_ui/cli/commands.py
streamdeck_ui/cli/server.py
streamdeck_ui/config.py
streamdeck_ui/dimmer.py
streamdeck_ui/display/__init__.py
streamdeck_ui/display/background_color_filter.py
streamdeck_ui/display/display_grid.py
streamdeck_ui/display/empty_filter.py
streamdeck_ui/display/filter.py
streamdeck_ui/display/image_filter.py
streamdeck_ui/display/keypress_filter.py
streamdeck_ui/display/pipeline.py
streamdeck_ui/display/pulse_filter.py
streamdeck_ui/display/text_filter.py
streamdeck_ui/fonts/roboto/LICENSE.txt
streamdeck_ui/fonts/roboto/Roboto-Black.ttf
streamdeck_ui/fonts/roboto/Roboto-BlackItalic.ttf
streamdeck_ui/fonts/roboto/Roboto-Bold.ttf
streamdeck_ui/fonts/roboto/Roboto-BoldItalic.ttf
streamdeck_ui/fonts/roboto/Roboto-Italic.ttf
streamdeck_ui/fonts/roboto/Roboto-Light.ttf
streamdeck_ui/fonts/roboto/Roboto-LightItalic.ttf
streamdeck_ui/fonts/roboto/Roboto-Medium.ttf
streamdeck_ui/fonts/roboto/Roboto-MediumItalic.ttf
streamdeck_ui/fonts/roboto/Roboto-Regular.ttf
streamdeck_ui/fonts/roboto/Roboto-Thin.ttf
streamdeck_ui/fonts/roboto/Roboto-ThinItalic.ttf
streamdeck_ui/gui.py
streamdeck_ui/icons/add_page.png
streamdeck_ui/icons/cross.png
streamdeck_ui/icons/gear.png
streamdeck_ui/icons/horizontal-align.png
streamdeck_ui/icons/remove_page.png
streamdeck_ui/icons/vertical-align.png
streamdeck_ui/icons/warning_icon_button.png
streamdeck_ui/logger.py
streamdeck_ui/logo.png
streamdeck_ui/main.ui
streamdeck_ui/mock_streamdeck.py
streamdeck_ui/model.py
streamdeck_ui/modules/__init__.py
streamdeck_ui/modules/fonts.py
streamdeck_ui/modules/keyboard.py
streamdeck_ui/modules/utils/__init__.py
streamdeck_ui/modules/utils/timers.py
streamdeck_ui/plugin_system/__init__.py
streamdeck_ui/plugin_system/base_plugin.py
streamdeck_ui/plugin_system/plugin_manager.py
streamdeck_ui/plugin_system/protocol.py
streamdeck_ui/plugin_system/schema.py
streamdeck_ui/resources.qrc
streamdeck_gui_ng-4.4.3.dist-info/METADATA
streamdeck_gui_ng-4.4.3.dist-info/WHEEL
streamdeck_gui_ng-4.4.3.dist-info/entry_points.txt
streamdeck_gui_ng-4.4.3.dist-info/licenses/LICENSE
streamdeck_gui_ng-4.4.3.dist-info/RECORD
