Metadata-Version: 2.4
Name: streamdeck-gui-ng
Version: 4.4.3
Summary: Next Generation Linux UI for the Elgato Stream Deck - Modernized fork with Python 3.11+ support
License: MIT
License-File: LICENSE
Author: Timothy Crosley
Author-email: timothy.crosley@gmail.com
Maintainer: millaguie
Maintainer-email: millaguie@users.noreply.github.com
Requires-Python: >=3.11,<3.14
Classifier: License :: OSI Approved :: MIT License
Classifier: Programming Language :: Python :: 3
Classifier: Programming Language :: Python :: 3.11
Classifier: Programming Language :: Python :: 3.12
Classifier: Programming Language :: Python :: 3.13
Requires-Dist: CairoSVG (>=2.5.2,<3.0.0)
Requires-Dist: evdev (>=1.6.1,<2.0.0)
Requires-Dist: filetype (>=1.0.10,<2.0.0)
Requires-Dist: importlib-metadata (>=6.8.0,<7.0.0)
Requires-Dist: pillow (>=10.3.0)
Requires-Dist: pyside6 (>=6.4.2,<7.0.0)
Requires-Dist: pyyaml (>=6.0,<7.0)
Requires-Dist: requests (>=2.31.0,<3.0.0)
Requires-Dist: streamdeck (>=0.9.5,<0.10.0)
